egse/coordinates/__init__.py
egse/coordinates/avoidance.py
egse/coordinates/cslmodel.py
egse/coordinates/laser_tracker_to_dict.py
egse/coordinates/point.py
egse/coordinates/pyplot.py
egse/coordinates/referenceFrame.py
egse/coordinates/refmodel.py
egse/coordinates/rotationMatrix.py
egse/coordinates/transform3d_addon.py
cgse_coordinates-2025.0.9.dist-info/METADATA
cgse_coordinates-2025.0.9.dist-info/WHEEL
cgse_coordinates-2025.0.9.dist-info/entry_points.txt
cgse_coordinates-2025.0.9.dist-info/RECORD
