Metadata-Version: 2.4
Name: cgse-coordinates
Version: 2025.0.9
Summary: Reference Frames and Coordinate Transofrmations for CGSE
Author-email: Rik Huygen <rik.huygen@kuleuven.be>, Sara Regibo <sara.regibo@kuleuven.be>
License-Expression: MIT
Keywords: CGSE,Common-EGSE,hardware testing,reference frames,software framework
Requires-Python: >=3.9
Requires-Dist: cgse-common
Requires-Dist: cgse-core
Requires-Dist: numpy==1.22.4
Requires-Dist: pandas>=1.5.1
Requires-Dist: pip>=24.3.1
Requires-Dist: transforms3d>=0.4.2
Provides-Extra: dev
Requires-Dist: pytest; extra == 'dev'
Requires-Dist: pytest-cov; extra == 'dev'
Requires-Dist: pytest-mock; extra == 'dev'
